wayOfChange/.idea/.gitignore
wayOfChange/.idea/inspectionProfiles/profiles_settings.xml
wayOfChange/.idea/misc.xml
wayOfChange/.idea/modules.xml
wayOfChange/.idea/vcs.xml
wayOfChange/.idea/wayOfChange.iml
wayOfChange/.idea/workspace.xml
wayOfChange/ADD-JAZZ.TTF
wayOfChange/ANTSYPAN.TTF
wayOfChange/AbrilFatface-Regular.ttf
wayOfChange/Almonte Regular.ttf
wayOfChange/Almonte.ttf
wayOfChange/BadMofo.ttf
wayOfChange/BohemianTypewriter.ttf
wayOfChange/Book.py
wayOfChange/Braille.py
wayOfChange/Change.py
wayOfChange/Chord.py
wayOfChange/Codon.py
wayOfChange/Colour.py
wayOfChange/DejaVuMathTeXGyre.ttf
wayOfChange/DejaVuSans-Bold.ttf
wayOfChange/DejaVuSans-BoldOblique.ttf
wayOfChange/DejaVuSans-ExtraLight.ttf
wayOfChange/DejaVuSans-Oblique.ttf
wayOfChange/DejaVuSans.ttf
wayOfChange/DejaVuSansCondensed-Bold.ttf
wayOfChange/DejaVuSansCondensed-BoldOblique.ttf
wayOfChange/DejaVuSansCondensed-Oblique.ttf
wayOfChange/DejaVuSansCondensed.ttf
wayOfChange/DejaVuSansMono-Bold.ttf
wayOfChange/DejaVuSansMono-BoldOblique.ttf
wayOfChange/DejaVuSansMono-Oblique.ttf
wayOfChange/DejaVuSansMono.ttf
wayOfChange/DejaVuSerif-Bold.ttf
wayOfChange/DejaVuSerif-BoldItalic.ttf
wayOfChange/DejaVuSerif-Italic.ttf
wayOfChange/DejaVuSerif.ttf
wayOfChange/DejaVuSerifCondensed-Bold.ttf
wayOfChange/DejaVuSerifCondensed-BoldItalic.ttf
wayOfChange/DejaVuSerifCondensed-Italic.ttf
wayOfChange/DejaVuSerifCondensed.ttf
wayOfChange/DorovarFLF-Carolus.ttf
wayOfChange/DorovarflfCarolus-axyg.ttf
wayOfChange/DorovarflfItalic-EaX8.ttf
wayOfChange/EmojiSymbols-Regular.ttf
wayOfChange/FCircle.py
wayOfChange/FontMap.py
wayOfChange/FrakturShadowed.ttf
wayOfChange/Fretboard.py
wayOfChange/GrafikText.ttf
wayOfChange/GramophoneNF.TTF
wayOfChange/Graphics.py
wayOfChange/Hexagram.py
wayOfChange/HeyAugust-VGOqe.ttf
wayOfChange/JAZZTEXT.TTF
wayOfChange/JazzNote.py
wayOfChange/Key.py
wayOfChange/L Italic.ttf
wayOfChange/Latex.py
wayOfChange/MonkeyFingersNF.ttf
wayOfChange/NGramGraphic.py
wayOfChange/Project.py
wayOfChange/wayOfChange.egg-info/PKG-INFO
wayOfChange/wayOfChange.egg-info/SOURCES.txt
wayOfChange/wayOfChange.egg-info/dependency_links.txt
wayOfChange/wayOfChange.egg-info/entry_points.txt
wayOfChange/wayOfChange.egg-info/top_level.txt
wayofchange-0.0.55.dist-info/LICENSE
wayofchange-0.0.55.dist-info/WHEEL
wayofchange-0.0.55.dist-info/METADATA
wayofchange-0.0.55.dist-info/RECORD
