Metadata-Version: 2.1
Name: wayofchange
Version: 0.0.55
Summary: Python suite for music theory analysis and LaTeX outputs.
Author: Edrihan Levesque
Author-email: edrihan@gmail.com
Requires-Python: >=3.8,<4.0
Classifier: Programming Language :: Python :: 3
Classifier: Programming Language :: Python :: 3.8
Classifier: Programming Language :: Python :: 3.9
Classifier: Programming Language :: Python :: 3.10
Classifier: Programming Language :: Python :: 3.11
Requires-Dist: python-polylabel
Requires-Dist: pyx
